verifyo/__init__.py
verifyo/client.py
verifyo/exceptions/__init__.py
verifyo/exceptions/api.py
verifyo/exceptions/auth.py
verifyo/exceptions/base.py
verifyo/exceptions/network.py
verifyo/exceptions/rate_limit.py
verifyo/models/__init__.py
verifyo/models/aml_screening.py
verifyo/models/check_response.py
verifyo/models/rate_limit_info.py
verifyo/models/verification_result.py
verifyo/models/wallet_info.py
verifyo-1.0.0.dist-info/METADATA
verifyo-1.0.0.dist-info/WHEEL
verifyo-1.0.0.dist-info/top_level.txt
verifyo-1.0.0.dist-info/RECORD
