Metadata-Version: 2.4
Name: verifyo
Version: 1.0.0
Summary: Official Python SDK for Verifyo Zero-Knowledge KYC API
Author-email: Verifyo Team <developers@verifyo.com>
Project-URL: Homepage, https://verifyo.com
Project-URL: Documentation, https://verifyo.com/docs
Project-URL: Repository, https://github.com/verifyo-dot-com/verifyo-python-sdk
Project-URL: Bug Tracker, https://github.com/verifyo-dot-com/verifyo-python-sdk/issues
Keywords: kyc,verification,identity,crypto,blockchain,compliance,aml,zero-knowledge
Classifier: Development Status :: 5 - Production/Stable
Classifier: Intended Audience :: Developers
Classifier: Programming Language :: Python :: 3
Classifier: Programming Language :: Python :: 3.8
Classifier: Programming Language :: Python :: 3.9
Classifier: Programming Language :: Python :: 3.10
Classifier: Programming Language :: Python :: 3.11
Classifier: Programming Language :: Python :: 3.12
Classifier: Topic :: Internet :: WWW/HTTP
Classifier: Topic :: Software Development :: Libraries :: Python Modules
Classifier: Topic :: Security
Classifier: Topic :: Office/Business :: Financial
Requires-Python: >=3.8
Requires-Dist: requests>=2.25.0
Requires-Dist: typing-extensions>=4.0.0
Provides-Extra: async
Requires-Dist: aiohttp>=3.8.0; extra == "async"
Provides-Extra: dev
Requires-Dist: pytest>=7.0.0; extra == "dev"
Requires-Dist: pytest-cov>=4.0.0; extra == "dev"
Requires-Dist: pytest-asyncio>=0.21.0; extra == "dev"
Requires-Dist: black>=22.0.0; extra == "dev"
Requires-Dist: flake8>=5.0.0; extra == "dev"
Requires-Dist: mypy>=1.0.0; extra == "dev"
Requires-Dist: types-requests>=2.25.0; extra == "dev"
